test/__init__.py
test/test_parser.py
unicornclient/__init__.py
unicornclient/agent.py
unicornclient/client.py
unicornclient/config.py
unicornclient/handler.py
unicornclient/manager.py
unicornclient/message.py
unicornclient/mission.py
unicornclient/mqtt_client.py
unicornclient/mqtt_sender.py
unicornclient/parser.py
unicornclient/routine.py
unicornclient/sender.py
unicornclient/spy.py
unicornclient/spy_volt.py
unicornclient/version.py
unicornclient/routines/__init__.py
unicornclient/routines/auth.py
unicornclient/routines/ping.py
unicornclient/routines/status.py
unicornclient/routines/system.py
unicornclient-5.2.1.dist-info/LICENSE
unicornclient-5.2.1.dist-info/METADATA
unicornclient-5.2.1.dist-info/WHEEL
unicornclient-5.2.1.dist-info/entry_points.txt
unicornclient-5.2.1.dist-info/top_level.txt
unicornclient-5.2.1.dist-info/RECORD
