Metadata-Version: 2.1
Name: unicornclient
Version: 5.2.1
Summary: Unicorn client
Home-page: https://github.com/amm0nite/unicornclient
Author: Pierre Cavan
Author-email: ammonite.myfox@gmail.com
License: MIT
Keywords: Raspberry Pi
Classifier: Development Status :: 3 - Alpha
Classifier: Operating System :: POSIX :: Linux
Classifier: License :: OSI Approved :: MIT License
Classifier: Intended Audience :: Developers
Classifier: Programming Language :: Python :: 3
Classifier: Topic :: Software Development
Classifier: Topic :: System :: Hardware
License-File: LICENSE
Requires-Dist: paho-mqtt (>=2.0.0)
